cdshelper/__init__.py
cdshelper/demo.py
cdshelper/cli/__init__.py
cdshelper/cli/cli.py
cdshelper/cli/get.py
cdshelper/cli/request.py
cdshelper/cli/template.py
cdshelper/core/__init__.py
cdshelper/core/core.py
cds_helper-0.0.1a2.dist-info/METADATA
cds_helper-0.0.1a2.dist-info/WHEEL
cds_helper-0.0.1a2.dist-info/entry_points.txt
cds_helper-0.0.1a2.dist-info/top_level.txt
cds_helper-0.0.1a2.dist-info/RECORD
