Metadata-Version: 2.4
Name: cds-helper
Version: 0.0.1a2
Summary: Chris' Dataset Helper - Utilities for retrieving climate datasets
Author-email: Chris McBride <chris@quizzical.ai>
License-Expression: Apache-2.0
Project-URL: repository, https://github.com/ankona/cds-helper
Project-URL: homepage, https://www.quizzical.ai/cdshelper
Keywords: MCDR,CDR,ocean,climate,dataset
Requires-Python: >=3.10
Requires-Dist: cdsapi>=0.7.6
Requires-Dist: pydantic<2.20,>=2.11.5
Provides-Extra: test
Requires-Dist: pytest>=7.0; extra == "test"
Provides-Extra: dev
Requires-Dist: ruff<0.20,>=0.11.13; extra == "dev"
Requires-Dist: mypy<1.20,>=1.16.0; extra == "dev"
